logicalnn/__init__.py
logicalnn/scripts/__init__.py
logicalnn/scripts/andGate.py
logicalnn/scripts/nandGate.py
logicalnn/scripts/norGate.py
logicalnn/scripts/notGate.py
logicalnn/scripts/orGate.py
logicalnn-0.0.0.dist-info/METADATA
logicalnn-0.0.0.dist-info/WHEEL
logicalnn-0.0.0.dist-info/top_level.txt
logicalnn-0.0.0.dist-info/RECORD
